[
  {
    "id": "paynex-api-1",
    "title": "iPhone 14 Pro Max - 256GB",
    "price": 49950,
    "oldPrice": 55000,
    "description": "شاشة Super Retina XDR مقاس 6.7 بوصة ميزة تشغيل دائم، كاميرا رئيسية بدقة 48 ميجابكسل، وشريحة A16 Bionic خارقة الذكاء.",
    "images": [
      "https://images.unsplash.com/photo-1678652197831-2d180705cd2c?w=500"
    ],
    "store": "Apple Store",
    "url": "https://dummyjson.com/products/1",
    "scrapedAt": "2026-05-19T10:33:00Z"
  },
  {
    "id": "paynex-api-2",
    "title": "Samsung Galaxy S23 Ultra",
    "price": 44990,
    "oldPrice": 49000,
    "description": "قلم S Pen مدمج، كاميرا بدقة 200 ميجابكسل للتصوير الليلي الاحترافي، ومعالج Snapdragon 8 Gen 2 لأقوى أداء ألعاب.",
    "images": [
      "https://images.unsplash.com/photo-1610945265064-0e34e5519bbf?w=500"
    ],
    "store": "Samsung Global",
    "url": "https://dummyjson.com/products/2",
    "scrapedAt": "2026-05-19T10:33:00Z"
  },
  {
    "id": "paynex-api-3",
    "title": "Xiaomi Redmi Note 12 Pro",
    "price": 14500,
    "oldPrice": 16000,
    "description": "شاشة أموليد 120 هرتز، شحن سريع بقوة 67 واط، وكاميرا ثلاثية بدقة 50 ميجابكسل مع مثبت بصري ذكي.",
    "images": [
      "https://images.unsplash.com/photo-1598327105666-5b89351aff97?w=500"
    ],
    "store": "Xiaomi Store",
    "url": "https://dummyjson.com/products/3",
    "scrapedAt": "2026-05-19T10:33:00Z"
  },
  {
    "id": "paynex-api-4",
    "title": "Realme GT Neo 5",
    "price": 19200,
    "oldPrice": 19200,
    "description": "شاحن خارق بقوة 150 واط يشحن الهاتف في 15 دقيقة، ذاكرة عشوائية 16 جيجا رام، وتصميم خلفي بإضاءة RGB تفاعلية.",
    "images": [
      "https://images.unsplash.com/photo-1511707171634-5f897ff02aa9?w=500"
    ],
    "store": "Realme",
    "url": "https://dummyjson.com/products/4",
    "scrapedAt": "2026-05-19T10:33:00Z"
  }
]
